Metadata-Version: 2.1
Name: odoo13-addon-l10n-es-dua-ticketbai-batuz
Version: 13.0.1.0.1.dev3
Summary: TicketBAI - Batuz con DUA
Home-page: https://github.com/OCA/l10n-spain
Author: Landoo Sistemas de Información S.L, Odoo Community Association (OCA)
Author-email: support@odoo-community.org
License: AGPL-3
Platform: UNKNOWN
Classifier: Programming Language :: Python
Classifier: Framework :: Odoo
Classifier: Framework :: Odoo :: 13.0
Classifier: License :: OSI Approved :: GNU Affero General Public License v3
Classifier: Development Status :: 3 - Alpha
Requires-Python: >=3.5
Requires-Dist: odoo13-addon-l10n-es-dua
Requires-Dist: odoo13-addon-l10n-es-ticketbai-batuz
Requires-Dist: odoo <13.1dev,>=13.0a
